fastring.cpython-312-x86_64-linux-gnu.so
sensor_core/sensor_manager.py
sensor_core/__init__.py
sensor_core/dsp/dsp_manager.py
sensor_core/dsp/__init__.py
sensor_core/utils/metrics.py
sensor_core/utils/utils.py
sensor_core/utils/__init__.py
sensor_core/data/data_manager.py
sensor_core/data/__init__.py
sensor_core/serial/__init__.py
sensor_core/serial/ser_manager.py
sensor_core/native/fastring/ring.hpp
sensor_core/native/fastring/py_module.cpp
sensor_core/plot/plot_utils.py
sensor_core/plot/plot_manager.py
sensor_core/plot/__init__.py
sensor_core/memory/db_ingester.py
sensor_core/memory/ring_adapter.py
sensor_core/memory/strg_manager.py
sensor_core/memory/stream_logger.py
sensor_core/memory/mem_utils.py
sensor_core/memory/__init__.py
sensor_pipeline-1.0.0.dist-info/WHEEL
sensor_pipeline-1.0.0.dist-info/top_level.txt
sensor_pipeline-1.0.0.dist-info/METADATA
sensor_pipeline-1.0.0.dist-info/RECORD
sensor_pipeline-1.0.0.dist-info/licenses/LICENSE
