Metadata-Version: 2.4
Name: sensor_pipeline
Version: 1.0.0
Summary: Core API for acquiring, processing, visualizing, and storing sensor data in real-time
License:                                  Apache License
Requires-Python: >=3.10
License-File: LICENSE
Requires-Dist: numpy
Requires-Dist: pygfx>=0.1.13
Requires-Dist: jupyterlab
Requires-Dist: pyserial
Requires-Dist: fastplotlib
Requires-Dist: sqlitedict
Requires-Dist: pybind11
Dynamic: license-file
